Workbook

Sheet Controls
A1: Control | B1: Value | C1: Purpose
A2: High Variance Threshold | B2: 0.15 | C2: Flags severe exceptions
A3: Medium Variance Threshold | B3: 0.08 | C3: Flags medium exceptions
A4: Low Variance Threshold | B4: 0.03 | C4: Flags low exceptions
A5: Trend Periods | B5: 3 | C5: Lookback window for patterns
A7: Pattern logic | B7: Uses variance thresholds plus 3-period trend direction.
A8: Severity logic | B8: High >= high threshold, Medium >= medium threshold, Low >= low threshold.
A9: Generated On | B9: 2026-04-22T18:27:57 | C9: Report generation timestamp
A10: Dimension Count | B10: 9 | C10: Dimensions discovered in environment
A11: Dimensions | B11: Measures, Period, Years, Scenario, Version, Entity, UoM, LOB, Analysis | C11: Discovered dimensions
A12: Severity Logic | B12: High >= 20%, Medium >= 10%, else Low | C12: Threshold rule
A13: Trend Logic | B13: Up: Actual>Forecast, Down: Actual<Forecast, Flat: equal | C13: Trend rule
A14: Pattern Logic | B14: Stable if |Var %| < 5 else Deviation | C14: Pattern rule
A15: Note | B15: Entity L0 descendants under parent 'DO NOT USE': 22 | C15: Generation note
A16: Note | B16: Measures L0 descendants under parent 'Profit and Loss Statement': 18 | C16: Generation note
A17: Note | B17: Period L0 descendants under parent 'YearTotal': 12 | C17: Generation note
A18: Note | B18: Scenarios filter: ['Actual', 'Forecast'] | C18: Generation note
A19: Note | B19: Years filter: ['FY24', 'FY25', 'FY26', 'FY27', 'FY28', 'FY29'] | C19: Generation note
A20: Note | B20: Version filter: ['Sample_Actual'] | C20: Generation note
A21: Note | B21: Location=Total_Location_Input, UoM=No UoM, LOB=No LOB, Energy Type=Pollutant 1 | C21: Generation note
A22: Note | B22: Prior 1 and Prior 2 derived from Actual scenario for years FY26-1 and FY26-2 | C22: Generation note

Sheet Data
A1: Entity | B1: Account | C1: Actual | D1: Forecast | E1: Prior 1 | F1: Prior 2 | G1: Variance | H1: Var % | I1: Trend | J1: Pattern | K1: Severity | L1: Narrative Message | M1: Recommended Action
A2: North | B2: Revenue | C2: 1250 | D2: 1100 | E2: 1180 | F2: 1130 | G2: =C2-D2 | H2: =IFERROR(G2/D2,0) | I2: =IF(AND(C2>E2,E2>F2),"Uptrend",IF(AND(C2<E2,E2<F2),"Downtrend","Flat/volatile")) | J2: =IF(ABS(H2)>=Controls!$B$2,"Outlier",IF(AND(H2>Controls!$B$4,I2="Uptrend"),"Sustained upside",IF(AND(H2<-Controls!$B$4,I2="Downtrend"),"Sustained downside",IF(AND(ABS(H2)>Controls!$B$4,I2="Flat/volatile"),"Forecast bias","On track")))) | K2: =IF(ABS(H2)>=Controls!$B$2,"High",IF(ABS(H2)>=Controls!$B$3,"Medium",IF(ABS(H2)>=Controls!$B$4,"Low","None"))) | L2: =IF(J2="Outlier","Value is outside the normal band and should be validated.",IF(J2="Sustained upside","Actual is above forecast for 3 consecutive periods. Pattern suggests stronger-than-planned performance.",IF(J2="Sustained downside","Actual is below forecast for 3 consecutive periods. Forecast may be overstated.",IF(J2="Forecast bias","Forecast is consistently optimistic versus actuals.",IF(J2="On track","Actual is aligned with forecast.","Review required."))))) | M2: =IF(K2="High","Escalate to owner and reforecast.",IF(K2="Medium","Review assumptions and adjust plan.",IF(K2="Low","Monitor next cycle.","No action required.")))
A3: North | B3: Opex | C3: 420 | D3: 390 | E3: 382 | F3: 375 | G3: =C3-D3 | H3: =IFERROR(G3/D3,0) | I3: =IF(AND(C3>E3,E3>F3),"Uptrend",IF(AND(C3<E3,E3<F3),"Downtrend","Flat/volatile")) | J3: =IF(ABS(H3)>=Controls!$B$2,"Outlier",IF(AND(H3>Controls!$B$4,I3="Uptrend"),"Sustained upside",IF(AND(H3<-Controls!$B$4,I3="Downtrend"),"Sustained downside",IF(AND(ABS(H3)>Controls!$B$4,I3="Flat/volatile"),"Forecast bias","On track")))) | K3: =IF(ABS(H3)>=Controls!$B$2,"High",IF(ABS(H3)>=Controls!$B$3,"Medium",IF(ABS(H3)>=Controls!$B$4,"Low","None"))) | L3: =IF(J3="Outlier","Value is outside the normal band and should be validated.",IF(J3="Sustained upside","Actual is above forecast for 3 consecutive periods. Pattern suggests stronger-than-planned performance.",IF(J3="Sustained downside","Actual is below forecast for 3 consecutive periods. Forecast may be overstated.",IF(J3="Forecast bias","Forecast is consistently optimistic versus actuals.",IF(J3="On track","Actual is aligned with forecast.","Review required."))))) | M3: =IF(K3="High","Escalate to owner and reforecast.",IF(K3="Medium","Review assumptions and adjust plan.",IF(K3="Low","Monitor next cycle.","No action required.")))
A4: West | B4: Revenue | C4: 980 | D4: 1080 | E4: 1045 | F4: 1112 | G4: =C4-D4 | H4: =IFERROR(G4/D4,0) | I4: =IF(AND(C4>E4,E4>F4),"Uptrend",IF(AND(C4<E4,E4<F4),"Downtrend","Flat/volatile")) | J4: =IF(ABS(H4)>=Controls!$B$2,"Outlier",IF(AND(H4>Controls!$B$4,I4="Uptrend"),"Sustained upside",IF(AND(H4<-Controls!$B$4,I4="Downtrend"),"Sustained downside",IF(AND(ABS(H4)>Controls!$B$4,I4="Flat/volatile"),"Forecast bias","On track")))) | K4: =IF(ABS(H4)>=Controls!$B$2,"High",IF(ABS(H4)>=Controls!$B$3,"Medium",IF(ABS(H4)>=Controls!$B$4,"Low","None"))) | L4: =IF(J4="Outlier","Value is outside the normal band and should be validated.",IF(J4="Sustained upside","Actual is above forecast for 3 consecutive periods. Pattern suggests stronger-than-planned performance.",IF(J4="Sustained downside","Actual is below forecast for 3 consecutive periods. Forecast may be overstated.",IF(J4="Forecast bias","Forecast is consistently optimistic versus actuals.",IF(J4="On track","Actual is aligned with forecast.","Review required."))))) | M4: =IF(K4="High","Escalate to owner and reforecast.",IF(K4="Medium","Review assumptions and adjust plan.",IF(K4="Low","Monitor next cycle.","No action required.")))
A5: East | B5: Margin % | C5: 0.182 | D5: 0.21 | E5: 0.225 | F5: 0.228 | G5: =C5-D5 | H5: =IFERROR(G5/D5,0) | I5: =IF(AND(C5>E5,E5>F5),"Uptrend",IF(AND(C5<E5,E5<F5),"Downtrend","Flat/volatile")) | J5: =IF(ABS(H5)>=Controls!$B$2,"Outlier",IF(AND(H5>Controls!$B$4,I5="Uptrend"),"Sustained upside",IF(AND(H5<-Controls!$B$4,I5="Downtrend"),"Sustained downside",IF(AND(ABS(H5)>Controls!$B$4,I5="Flat/volatile"),"Forecast bias","On track")))) | K5: =IF(ABS(H5)>=Controls!$B$2,"High",IF(ABS(H5)>=Controls!$B$3,"Medium",IF(ABS(H5)>=Controls!$B$4,"Low","None"))) | L5: =IF(J5="Outlier","Value is outside the normal band and should be validated.",IF(J5="Sustained upside","Actual is above forecast for 3 consecutive periods. Pattern suggests stronger-than-planned performance.",IF(J5="Sustained downside","Actual is below forecast for 3 consecutive periods. Forecast may be overstated.",IF(J5="Forecast bias","Forecast is consistently optimistic versus actuals.",IF(J5="On track","Actual is aligned with forecast.","Review required."))))) | M5: =IF(K5="High","Escalate to owner and reforecast.",IF(K5="Medium","Review assumptions and adjust plan.",IF(K5="Low","Monitor next cycle.","No action required.")))
A6: South | B6: Capex | C6: 210 | D6: 140 | E6: 135 | F6: 133 | G6: =C6-D6 | H6: =IFERROR(G6/D6,0) | I6: =IF(AND(C6>E6,E6>F6),"Uptrend",IF(AND(C6<E6,E6<F6),"Downtrend","Flat/volatile")) | J6: =IF(ABS(H6)>=Controls!$B$2,"Outlier",IF(AND(H6>Controls!$B$4,I6="Uptrend"),"Sustained upside",IF(AND(H6<-Controls!$B$4,I6="Downtrend"),"Sustained downside",IF(AND(ABS(H6)>Controls!$B$4,I6="Flat/volatile"),"Forecast bias","On track")))) | K6: =IF(ABS(H6)>=Controls!$B$2,"High",IF(ABS(H6)>=Controls!$B$3,"Medium",IF(ABS(H6)>=Controls!$B$4,"Low","None"))) | L6: =IF(J6="Outlier","Value is outside the normal band and should be validated.",IF(J6="Sustained upside","Actual is above forecast for 3 consecutive periods. Pattern suggests stronger-than-planned performance.",IF(J6="Sustained downside","Actual is below forecast for 3 consecutive periods. Forecast may be overstated.",IF(J6="Forecast bias","Forecast is consistently optimistic versus actuals.",IF(J6="On track","Actual is aligned with forecast.","Review required."))))) | M6: =IF(K6="High","Escalate to owner and reforecast.",IF(K6="Medium","Review assumptions and adjust plan.",IF(K6="Low","Monitor next cycle.","No action required.")))
A7: Central | B7: Headcount | C7: 145 | D7: 146 | E7: 144 | F7: 145 | G7: =C7-D7 | H7: =IFERROR(G7/D7,0) | I7: =IF(AND(C7>E7,E7>F7),"Uptrend",IF(AND(C7<E7,E7<F7),"Downtrend","Flat/volatile")) | J7: =IF(ABS(H7)>=Controls!$B$2,"Outlier",IF(AND(H7>Controls!$B$4,I7="Uptrend"),"Sustained upside",IF(AND(H7<-Controls!$B$4,I7="Downtrend"),"Sustained downside",IF(AND(ABS(H7)>Controls!$B$4,I7="Flat/volatile"),"Forecast bias","On track")))) | K7: =IF(ABS(H7)>=Controls!$B$2,"High",IF(ABS(H7)>=Controls!$B$3,"Medium",IF(ABS(H7)>=Controls!$B$4,"Low","None"))) | L7: =IF(J7="Outlier","Value is outside the normal band and should be validated.",IF(J7="Sustained upside","Actual is above forecast for 3 consecutive periods. Pattern suggests stronger-than-planned performance.",IF(J7="Sustained downside","Actual is below forecast for 3 consecutive periods. Forecast may be overstated.",IF(J7="Forecast bias","Forecast is consistently optimistic versus actuals.",IF(J7="On track","Actual is aligned with forecast.","Review required."))))) | M7: =IF(K7="High","Escalate to owner and reforecast.",IF(K7="Medium","Review assumptions and adjust plan.",IF(K7="Low","Monitor next cycle.","No action required.")))
A8: LE_ANZ | B8: Product Revenue | C8: 0 | D8: 0 | E8: 0 | F8: 0 | G8: 0 | H8: 0 | I8: Flat | J8: Stable | K8: Low | L8: Product Revenue in LE_ANZ is 0.0% above forecast. | M8: Review drivers and adjust forecast assumptions.
A9: LE_ANZ | B9: Software Revenue | C9: 0 | D9: 0 | E9: 0 | F9: 0 | G9: 0 | H9: 0 | I9: Flat | J9: Stable | K9: Low | L9: Software Revenue in LE_ANZ is 0.0% above forecast. | M9: Review drivers and adjust forecast assumptions.
A10: LE_ANZ | B10: Hardware Revenue | C10: 0 | D10: 0 | E10: 0 | F10: 0 | G10: 0 | H10: 0 | I10: Flat | J10: Stable | K10: Low | L10: Hardware Revenue in LE_ANZ is 0.0% above forecast. | M10: Review drivers and adjust forecast assumptions.
A11: LE_ANZ | B11: Services Revenue | C11: 0 | D11: 0 | E11: 0 | F11: 0 | G11: 0 | H11: 0 | I11: Flat | J11: Stable | K11: Low | L11: Services Revenue in LE_ANZ is 0.0% above forecast. | M11: Review drivers and adjust forecast assumptions.
A12: LE_ANZ | B12: Dierct Cost of Sale | C12: 0 | D12: 0 | E12: 0 | F12: 0 | G12: 0 | H12: 0 | I12: Flat | J12: Stable | K12: Low | L12: Dierct Cost of Sale in LE_ANZ is 0.0% above forecast. | M12: Review drivers and adjust forecast assumptions.
A13: LE_ANZ | B13: Hardware costs | C13: 0 | D13: 0 | E13: 0 | F13: 0 | G13: 0 | H13: 0 | I13: Flat | J13: Stable | K13: Low | L13: Hardware costs in LE_ANZ is 0.0% above forecast. | M13: Review drivers and adjust forecast assumptions.
A14: LE_ANZ | B14: Services costs | C14: 0 | D14: 0 | E14: 0 | F14: 0 | G14: 0 | H14: 0 | I14: Flat | J14: Stable | K14: Low | L14: Services costs in LE_ANZ is 0.0% above forecast. | M14: Review drivers and adjust forecast assumptions.
A15: LE_ANZ | B15: Sales and Marketing costs | C15: 0 | D15: 0 | E15: 0 | F15: 0 | G15: 0 | H15: 0 | I15: Flat | J15: Stable | K15: Low | L15: Sales and Marketing costs in LE_ANZ is 0.0% above forecast. | M15: Review drivers and adjust forecast assumptions.
A16: LE_ANZ | B16: Research and development costs | C16: 0 | D16: 0 | E16: 0 | F16: 0 | G16: 0 | H16: 0 | I16: Flat | J16: Stable | K16: Low | L16: Research and development costs in LE_ANZ is 0.0% above forecast. | M16: Review drivers and adjust forecast assumptions.
A17: LE_ANZ | B17: General and administrative costs | C17: 0 | D17: 0 | E17: 0 | F17: 0 | G17: 0 | H17: 0 | I17: Flat | J17: Stable | K17: Low | L17: General and administrative costs in LE_ANZ is 0.0% above forecast. | M17: Review drivers and adjust forecast assumptions.
A18: LE_ANZ | B18: Amortization of intangible assets | C18: 0 | D18: 0 | E18: 0 | F18: 0 | G18: 0 | H18: 0 | I18: Flat | J18: Stable | K18: Low | L18: Amortization of intangible assets in LE_ANZ is 0.0% above forecast. | M18: Review drivers and adjust forecast assumptions.
A19: LE_ANZ | B19: Acquisition related and other costs | C19: 0 | D19: 0 | E19: 0 | F19: 0 | G19: 0 | H19: 0 | I19: Flat | J19: Stable | K19: Low | L19: Acquisition related and other costs in LE_ANZ is 0.0% above forecast. | M19: Review drivers and adjust forecast assumptions.
... A403: LE_USA | B403: Other comprehensive (loss) income | C403: 0 | D403: 0 | E403: 0 | F403: 0 | G403: 0 | H403: 0 | I403: Flat | J403: Stable | K403: Low | L403: Other comprehensive (loss) income in LE_USA is 0.0% above forecast. | M403: Review drivers and adjust forecast assumptions.

Sheet Summary
A1: EPM Actual vs Forecast Insight Summary
A2: Generated from the Data sheet using formulas.
A3: Total Insight Rows | B3: 396
A4: High Severity Count | B4: 0 | D4: Top Patterns | H4: Severity | I4: Count
A5: Medium Severity Count | B5: 0 | D5: Sustained upside | E5: =COUNTIF(Data!J2:J7,"Sustained upside") | H5: High | I5: =COUNTIF(Data!K2:K7,H5)
A6: Low Severity Count | B6: 396 | D6: Sustained downside | E6: =COUNTIF(Data!J2:J7,"Sustained downside") | H6: Medium | I6: =COUNTIF(Data!K2:K7,H6)
A7: Avg Var % | B7: 0 | D7: Forecast bias | E7: =COUNTIF(Data!J2:J7,"Forecast bias") | H7: Low | I7: =COUNTIF(Data!K2:K7,H7)
A8: Max |Var %| | B8: 0 | D8: Outlier | E8: =COUNTIF(Data!J2:J7,"Outlier")
A9: Medium Severity | B9: =COUNTIF(Data!K2:K7,"Medium")
A10: Low Severity | B10: =COUNTIF(Data!K2:K7,"Low")

Sheet Insights
A1: Actual vs Forecast Insights
A2: Business-friendly narrative view for stakeholders.
A3: Top 10 Variance Insights
A4: Entity | B4: Account | C4: Actual | D4: Forecast | E4: Variance | F4: Var % | G4: Severity | H4: Narrative Message | I4: Trend | J4: Pattern | K4: Severity | L4: Narrative Message | M4: Recommended Action
A5: LE_ANZ | B5: Product Revenue | C5: 0 | D5: 0 | E5: 0 | F5: 0 | G5: Low | H5: Product Revenue in LE_ANZ is 0.0% above forecast. | I5: =Data!I2 | J5: =Data!J2 | K5: =Data!K2 | L5: =Data!L2 | M5: =Data!M2
A6: LE_ANZ | B6: Software Revenue | C6: 0 | D6: 0 | E6: 0 | F6: 0 | G6: Low | H6: Software Revenue in LE_ANZ is 0.0% above forecast. | I6: =Data!I3 | J6: =Data!J3 | K6: =Data!K3 | L6: =Data!L3 | M6: =Data!M3
A7: LE_ANZ | B7: Hardware Revenue | C7: 0 | D7: 0 | E7: 0 | F7: 0 | G7: Low | H7: Hardware Revenue in LE_ANZ is 0.0% above forecast. | I7: =Data!I4 | J7: =Data!J4 | K7: =Data!K4 | L7: =Data!L4 | M7: =Data!M4
A8: LE_ANZ | B8: Services Revenue | C8: 0 | D8: 0 | E8: 0 | F8: 0 | G8: Low | H8: Services Revenue in LE_ANZ is 0.0% above forecast. | I8: =Data!I5 | J8: =Data!J5 | K8: =Data!K5 | L8: =Data!L5 | M8: =Data!M5
A9: LE_ANZ | B9: Dierct Cost of Sale | C9: 0 | D9: 0 | E9: 0 | F9: 0 | G9: Low | H9: Dierct Cost of Sale in LE_ANZ is 0.0% above forecast. | I9: =Data!I6 | J9: =Data!J6 | K9: =Data!K6 | L9: =Data!L6 | M9: =Data!M6
A10: LE_ANZ | B10: Hardware costs | C10: 0 | D10: 0 | E10: 0 | F10: 0 | G10: Low | H10: Hardware costs in LE_ANZ is 0.0% above forecast. | I10: =Data!I7 | J10: =Data!J7 | K10: =Data!K7 | L10: =Data!L7 | M10: =Data!M7
A11: LE_ANZ | B11: Services costs | C11: 0 | D11: 0 | E11: 0 | F11: 0 | G11: Low | H11: Services costs in LE_ANZ is 0.0% above forecast.
A12: LE_ANZ | B12: Sales and Marketing costs | C12: 0 | D12: 0 | E12: 0 | F12: 0 | G12: Low | H12: Sales and Marketing costs in LE_ANZ is 0.0% above forecast.
A13: LE_ANZ | B13: Research and development costs | C13: 0 | D13: 0 | E13: 0 | F13: 0 | G13: Low | H13: Research and development costs in LE_ANZ is 0.0% above forecast.
A14: LE_ANZ | B14: General and administrative costs | C14: 0 | D14: 0 | E14: 0 | F14: 0 | G14: Low | H14: General and administrative costs in LE_ANZ is 0.0% above forecast.
A15: 3. Update the Data tab and formulas refresh automatically in Excel.

Sheet README
A1: Template purpose
A2: Generate an exception-based Actual vs Forecast insight report from coded data inputs.
A4: Recommended process
A5: 1) Paste monthly or period data into the Data sheet.
A6: 2) Maintain 3 months of history for each row so trend formulas work.
A7: 3) Adjust thresholds on the Controls sheet.
A8: 4) Open the Summary and Insights tabs for the report output.
A10: Message examples
A11: Actual is above forecast for 3 consecutive periods.
A12: Forecast is consistently optimistic versus actuals.
A13: Value is outside the normal band and should be validated.
