Workbook

Sheet Controls
A1: Control | B1: Value | C1: Purpose
A2: High Variance Threshold | B2: 0.15 | C2: Flags severe exceptions
A3: Medium Variance Threshold | B3: 0.08 | C3: Flags medium exceptions
A4: Low Variance Threshold | B4: 0.03 | C4: Flags low exceptions
A5: Trend Periods | B5: 3 | C5: Lookback window for patterns
A7: Pattern logic | B7: Uses variance thresholds plus 3-period trend direction.
A8: Severity logic | B8: High >= high threshold, Medium >= medium threshold, Low >= low threshold.
A9: Generated On | B9: 2026-04-21T11:45:21 | C9: Report generation timestamp
A10: Dimension Count | B10: 9 | C10: Dimensions discovered in environment
A11: Dimensions | B11: Measures, Period, Years, Scenario, Version, Entity, UoM, LOB, Analysis | C11: Discovered dimensions

Sheet Data
A1: Entity | B1: Account | C1: Actual | D1: Forecast | E1: Prior 1 | F1: Prior 2 | G1: Variance | H1: Var % | I1: Trend | J1: Pattern | K1: Severity | L1: Narrative Message | M1: Recommended Action
A2: North | B2: Revenue | C2: 1250 | D2: 1100 | E2: 1180 | F2: 1130 | G2: =C2-D2 | H2: =IFERROR(G2/D2,0) | I2: =IF(AND(C2>E2,E2>F2),"Uptrend",IF(AND(C2<E2,E2<F2),"Downtrend","Flat/volatile")) | J2: =IF(ABS(H2)>=Controls!$B$2,"Outlier",IF(AND(H2>Controls!$B$4,I2="Uptrend"),"Sustained upside",IF(AND(H2<-Controls!$B$4,I2="Downtrend"),"Sustained downside",IF(AND(ABS(H2)>Controls!$B$4,I2="Flat/volatile"),"Forecast bias","On track")))) | K2: =IF(ABS(H2)>=Controls!$B$2,"High",IF(ABS(H2)>=Controls!$B$3,"Medium",IF(ABS(H2)>=Controls!$B$4,"Low","None"))) | L2: =IF(J2="Outlier","Value is outside the normal band and should be validated.",IF(J2="Sustained upside","Actual is above forecast for 3 consecutive periods. Pattern suggests stronger-than-planned performance.",IF(J2="Sustained downside","Actual is below forecast for 3 consecutive periods. Forecast may be overstated.",IF(J2="Forecast bias","Forecast is consistently optimistic versus actuals.",IF(J2="On track","Actual is aligned with forecast.","Review required."))))) | M2: =IF(K2="High","Escalate to owner and reforecast.",IF(K2="Medium","Review assumptions and adjust plan.",IF(K2="Low","Monitor next cycle.","No action required.")))
A3: North | B3: Opex | C3: 420 | D3: 390 | E3: 382 | F3: 375 | G3: =C3-D3 | H3: =IFERROR(G3/D3,0) | I3: =IF(AND(C3>E3,E3>F3),"Uptrend",IF(AND(C3<E3,E3<F3),"Downtrend","Flat/volatile")) | J3: =IF(ABS(H3)>=Controls!$B$2,"Outlier",IF(AND(H3>Controls!$B$4,I3="Uptrend"),"Sustained upside",IF(AND(H3<-Controls!$B$4,I3="Downtrend"),"Sustained downside",IF(AND(ABS(H3)>Controls!$B$4,I3="Flat/volatile"),"Forecast bias","On track")))) | K3: =IF(ABS(H3)>=Controls!$B$2,"High",IF(ABS(H3)>=Controls!$B$3,"Medium",IF(ABS(H3)>=Controls!$B$4,"Low","None"))) | L3: =IF(J3="Outlier","Value is outside the normal band and should be validated.",IF(J3="Sustained upside","Actual is above forecast for 3 consecutive periods. Pattern suggests stronger-than-planned performance.",IF(J3="Sustained downside","Actual is below forecast for 3 consecutive periods. Forecast may be overstated.",IF(J3="Forecast bias","Forecast is consistently optimistic versus actuals.",IF(J3="On track","Actual is aligned with forecast.","Review required."))))) | M3: =IF(K3="High","Escalate to owner and reforecast.",IF(K3="Medium","Review assumptions and adjust plan.",IF(K3="Low","Monitor next cycle.","No action required.")))
A4: West | B4: Revenue | C4: 980 | D4: 1080 | E4: 1045 | F4: 1112 | G4: =C4-D4 | H4: =IFERROR(G4/D4,0) | I4: =IF(AND(C4>E4,E4>F4),"Uptrend",IF(AND(C4<E4,E4<F4),"Downtrend","Flat/volatile")) | J4: =IF(ABS(H4)>=Controls!$B$2,"Outlier",IF(AND(H4>Controls!$B$4,I4="Uptrend"),"Sustained upside",IF(AND(H4<-Controls!$B$4,I4="Downtrend"),"Sustained downside",IF(AND(ABS(H4)>Controls!$B$4,I4="Flat/volatile"),"Forecast bias","On track")))) | K4: =IF(ABS(H4)>=Controls!$B$2,"High",IF(ABS(H4)>=Controls!$B$3,"Medium",IF(ABS(H4)>=Controls!$B$4,"Low","None"))) | L4: =IF(J4="Outlier","Value is outside the normal band and should be validated.",IF(J4="Sustained upside","Actual is above forecast for 3 consecutive periods. Pattern suggests stronger-than-planned performance.",IF(J4="Sustained downside","Actual is below forecast for 3 consecutive periods. Forecast may be overstated.",IF(J4="Forecast bias","Forecast is consistently optimistic versus actuals.",IF(J4="On track","Actual is aligned with forecast.","Review required."))))) | M4: =IF(K4="High","Escalate to owner and reforecast.",IF(K4="Medium","Review assumptions and adjust plan.",IF(K4="Low","Monitor next cycle.","No action required.")))
A5: East | B5: Margin % | C5: 0.182 | D5: 0.21 | E5: 0.225 | F5: 0.228 | G5: =C5-D5 | H5: =IFERROR(G5/D5,0) | I5: =IF(AND(C5>E5,E5>F5),"Uptrend",IF(AND(C5<E5,E5<F5),"Downtrend","Flat/volatile")) | J5: =IF(ABS(H5)>=Controls!$B$2,"Outlier",IF(AND(H5>Controls!$B$4,I5="Uptrend"),"Sustained upside",IF(AND(H5<-Controls!$B$4,I5="Downtrend"),"Sustained downside",IF(AND(ABS(H5)>Controls!$B$4,I5="Flat/volatile"),"Forecast bias","On track")))) | K5: =IF(ABS(H5)>=Controls!$B$2,"High",IF(ABS(H5)>=Controls!$B$3,"Medium",IF(ABS(H5)>=Controls!$B$4,"Low","None"))) | L5: =IF(J5="Outlier","Value is outside the normal band and should be validated.",IF(J5="Sustained upside","Actual is above forecast for 3 consecutive periods. Pattern suggests stronger-than-planned performance.",IF(J5="Sustained downside","Actual is below forecast for 3 consecutive periods. Forecast may be overstated.",IF(J5="Forecast bias","Forecast is consistently optimistic versus actuals.",IF(J5="On track","Actual is aligned with forecast.","Review required."))))) | M5: =IF(K5="High","Escalate to owner and reforecast.",IF(K5="Medium","Review assumptions and adjust plan.",IF(K5="Low","Monitor next cycle.","No action required.")))
A6: South | B6: Capex | C6: 210 | D6: 140 | E6: 135 | F6: 133 | G6: =C6-D6 | H6: =IFERROR(G6/D6,0) | I6: =IF(AND(C6>E6,E6>F6),"Uptrend",IF(AND(C6<E6,E6<F6),"Downtrend","Flat/volatile")) | J6: =IF(ABS(H6)>=Controls!$B$2,"Outlier",IF(AND(H6>Controls!$B$4,I6="Uptrend"),"Sustained upside",IF(AND(H6<-Controls!$B$4,I6="Downtrend"),"Sustained downside",IF(AND(ABS(H6)>Controls!$B$4,I6="Flat/volatile"),"Forecast bias","On track")))) | K6: =IF(ABS(H6)>=Controls!$B$2,"High",IF(ABS(H6)>=Controls!$B$3,"Medium",IF(ABS(H6)>=Controls!$B$4,"Low","None"))) | L6: =IF(J6="Outlier","Value is outside the normal band and should be validated.",IF(J6="Sustained upside","Actual is above forecast for 3 consecutive periods. Pattern suggests stronger-than-planned performance.",IF(J6="Sustained downside","Actual is below forecast for 3 consecutive periods. Forecast may be overstated.",IF(J6="Forecast bias","Forecast is consistently optimistic versus actuals.",IF(J6="On track","Actual is aligned with forecast.","Review required."))))) | M6: =IF(K6="High","Escalate to owner and reforecast.",IF(K6="Medium","Review assumptions and adjust plan.",IF(K6="Low","Monitor next cycle.","No action required.")))
A7: Central | B7: Headcount | C7: 145 | D7: 146 | E7: 144 | F7: 145 | G7: =C7-D7 | H7: =IFERROR(G7/D7,0) | I7: =IF(AND(C7>E7,E7>F7),"Uptrend",IF(AND(C7<E7,E7<F7),"Downtrend","Flat/volatile")) | J7: =IF(ABS(H7)>=Controls!$B$2,"Outlier",IF(AND(H7>Controls!$B$4,I7="Uptrend"),"Sustained upside",IF(AND(H7<-Controls!$B$4,I7="Downtrend"),"Sustained downside",IF(AND(ABS(H7)>Controls!$B$4,I7="Flat/volatile"),"Forecast bias","On track")))) | K7: =IF(ABS(H7)>=Controls!$B$2,"High",IF(ABS(H7)>=Controls!$B$3,"Medium",IF(ABS(H7)>=Controls!$B$4,"Low","None"))) | L7: =IF(J7="Outlier","Value is outside the normal band and should be validated.",IF(J7="Sustained upside","Actual is above forecast for 3 consecutive periods. Pattern suggests stronger-than-planned performance.",IF(J7="Sustained downside","Actual is below forecast for 3 consecutive periods. Forecast may be overstated.",IF(J7="Forecast bias","Forecast is consistently optimistic versus actuals.",IF(J7="On track","Actual is aligned with forecast.","Review required."))))) | M7: =IF(K7="High","Escalate to owner and reforecast.",IF(K7="Medium","Review assumptions and adjust plan.",IF(K7="Low","Monitor next cycle.","No action required.")))

Sheet Summary
A1: EPM Actual vs Forecast Insight Summary
A2: Generated from the Data sheet using formulas.
A3: Total Insight Rows | B3: 0
A4: High Severity Count | B4: 0 | D4: Top Patterns | H4: Severity | I4: Count
A5: Total Forecast | B5: =SUM(Data!D2:D7) | D5: Sustained upside | E5: =COUNTIF(Data!J2:J7,"Sustained upside") | H5: High | I5: =COUNTIF(Data!K2:K7,H5)
A6: Total Variance | B6: =SUM(Data!G2:G7) | D6: Sustained downside | E6: =COUNTIF(Data!J2:J7,"Sustained downside") | H6: Medium | I6: =COUNTIF(Data!K2:K7,H6)
A7: Variance % | B7: =IFERROR(B6/B5,0) | D7: Forecast bias | E7: =COUNTIF(Data!J2:J7,"Forecast bias") | H7: Low | I7: =COUNTIF(Data!K2:K7,H7)
A8: High Severity | B8: =COUNTIF(Data!K2:K7,"High") | D8: Outlier | E8: =COUNTIF(Data!J2:J7,"Outlier")
A9: Medium Severity | B9: =COUNTIF(Data!K2:K7,"Medium")
A10: Low Severity | B10: =COUNTIF(Data!K2:K7,"Low")

Sheet Insights
A1: Actual vs Forecast Insights
A2: Business-friendly narrative view for stakeholders.
A3: Top 10 Variance Insights
A4: Entity | B4: Account | C4: Actual | D4: Forecast | E4: Prior 1 | F4: Prior 2 | G4: Variance | H4: Var % | I4: Trend | J4: Pattern | K4: Severity | L4: Narrative Message | M4: Recommended Action
A5: =Data!A2 | B5: =Data!B2 | C5: =Data!C2 | D5: =Data!D2 | E5: =Data!E2 | F5: =Data!F2 | G5: =Data!G2 | H5: =Data!H2 | ... M5: =Data!M2
A6: =Data!A3 | B6: =Data!B3 | C6: =Data!C3 | D6: =Data!D3 | E6: =Data!E3 | F6: =Data!F3 | G6: =Data!G3 | H6: =Data!H3 | ... M6: =Data!M3
A7: =Data!A4 | B7: =Data!B4 | C7: =Data!C4 | D7: =Data!D4 | E7: =Data!E4 | F7: =Data!F4 | G7: =Data!G4 | H7: =Data!H4 | ... M7: =Data!M4
A8: =Data!A5 | B8: =Data!B5 | C8: =Data!C5 | D8: =Data!D5 | E8: =Data!E5 | F8: =Data!F5 | G8: =Data!G5 | H8: =Data!H5 | ... M8: =Data!M5
A9: =Data!A6 | B9: =Data!B6 | C9: =Data!C6 | D9: =Data!D6 | E9: =Data!E6 | F9: =Data!F6 | G9: =Data!G6 | H9: =Data!H6 | ... M9: =Data!M6
A10: =Data!A7 | B10: =Data!B7 | C10: =Data!C7 | D10: =Data!D7 | E10: =Data!E7 | F10: =Data!F7 | G10: =Data!G7 | H10: =Data!H7 | ... M10: =Data!M7
A12: How the report reads:
A13: 1. Use the Summary tab for totals and exception counts.
A14: 2. Use the Insights tab for row-by-row narrative messages.
A15: 3. Update the Data tab and formulas refresh automatically in Excel.

Sheet README
A1: Template purpose
A2: Generate an exception-based Actual vs Forecast insight report from coded data inputs.
A4: Recommended process
A5: 1) Paste monthly or period data into the Data sheet.
A6: 2) Maintain 3 months of history for each row so trend formulas work.
A7: 3) Adjust thresholds on the Controls sheet.
A8: 4) Open the Summary and Insights tabs for the report output.
A10: Message examples
A11: Actual is above forecast for 3 consecutive periods.
A12: Forecast is consistently optimistic versus actuals.
A13: Value is outside the normal band and should be validated.
